RSSPod_dl/__init__.py
RSSPod_dl/main.py
RSSPod_dl-1.0.2.dist-info/LICENSE
RSSPod_dl-1.0.2.dist-info/METADATA
RSSPod_dl-1.0.2.dist-info/WHEEL
RSSPod_dl-1.0.2.dist-info/entry_points.txt
RSSPod_dl-1.0.2.dist-info/top_level.txt
RSSPod_dl-1.0.2.dist-info/RECORD
