Metadata-Version: 2.1
Name: RSSPod-dl
Version: 1.0.2
Summary: Python CLI tool for downloading and managing podcast from RSS feeds.
Home-page: https://github.com/rimaout/RSSPod-dl
Author: mariout
License: MIT
Keywords: python,podcast downloader,RSS
Classifier: License :: OSI Approved :: MIT License
Classifier: Programming Language :: Python :: 3
Classifier: Operating System :: MacOS :: MacOS X
Classifier: Operating System :: Microsoft :: Windows
Classifier: Operating System :: POSIX :: Linux
License-File: LICENSE
Requires-Dist: bs4
Requires-Dist: eyed3
Requires-Dist: alive-progress
Requires-Dist: lxml
